ocp_project_plugin/__init__.py
ocp_project_plugin/api/nested_serializers.py
ocp_project_plugin/api/serializers.py
ocp_project_plugin/api/urls.py
ocp_project_plugin/api/views.py
ocp_project_plugin/apps.py
ocp_project_plugin/choices.py
ocp_project_plugin/filters/__init__.py
ocp_project_plugin/filters/app_environment.py
ocp_project_plugin/filters/ocp_project.py
ocp_project_plugin/forms/__init__.py
ocp_project_plugin/forms/bulk_edit.py
ocp_project_plugin/forms/bulk_import.py
ocp_project_plugin/forms/filtersets.py
ocp_project_plugin/forms/model_forms.py
ocp_project_plugin/migrations/0001_initial.py
ocp_project_plugin/migrations/__init__.py
ocp_project_plugin/mkdocs.yml
ocp_project_plugin/models/__init__.py
ocp_project_plugin/models/models.py
ocp_project_plugin/models/ocp_models.py
ocp_project_plugin/navigation.py
ocp_project_plugin/search.py
ocp_project_plugin/tables/__init__.py
ocp_project_plugin/tables/app_environment.py
ocp_project_plugin/tables/ocp_project.py
ocp_project_plugin/templates/ocp_project_plugin/app_environment/app_environment.html
ocp_project_plugin/templates/ocp_project_plugin/appenvironment.html
ocp_project_plugin/templates/ocp_project_plugin/ocp_project/base.html
ocp_project_plugin/templates/ocp_project_plugin/ocp_project/ocp_project.html
ocp_project_plugin/templates/ocp_project_plugin/ocpproject.html
ocp_project_plugin/templatetags/__init__.py
ocp_project_plugin/templatetags/settings.py
ocp_project_plugin/urls.py
ocp_project_plugin/views/__init__.py
ocp_project_plugin/views/app_environment.py
ocp_project_plugin/views/ocp_project.py
ocp_project_plugin/views/system_topography.py
ocp_project_plugin/worker.py
ocp_project_plugin-0.0.0.0.292.dist-info/WHEEL
ocp_project_plugin-0.0.0.0.292.dist-info/METADATA
ocp_project_plugin-0.0.0.0.292.dist-info/RECORD
