Metadata-Version: 2.1
Name: ocp-project-plugin
Version: 0.0.0.0.292
Summary: Netbox OCP Project Plugin
Author: Tim Rhomberg
Author-email: timrhomberg@hotmail.com
Requires-Python: >=3.8,<4.0
Classifier: Programming Language :: Python :: 3
Classifier: Programming Language :: Python :: 3.8
Classifier: Programming Language :: Python :: 3.9
Classifier: Programming Language :: Python :: 3.10
Classifier: Programming Language :: Python :: 3.11
Requires-Dist: gitpython (>=3.1.30,<4.0.0)
Requires-Dist: python-gitlab (>=3.13.0,<4.0.0)
